MANIFEST.in
README.rst
setup.py
djangosenchatools/__init__.py
djangosenchatools/auth.py
djangosenchatools/buildserver.py
djangosenchatools/models.py
djangosenchatools/watch.py
djangosenchatools.egg-info/PKG-INFO
djangosenchatools.egg-info/SOURCES.txt
djangosenchatools.egg-info/dependency_links.txt
djangosenchatools.egg-info/not-zip-safe
djangosenchatools.egg-info/requires.txt
djangosenchatools.egg-info/top_level.txt
djangosenchatools/management/__init__.py
djangosenchatools/management/commands/__init__.py
djangosenchatools/management/commands/senchatoolsbuild.py