Metadata-Version: 1.0
Name: djangosenchatools
Version: 1.0.5
Summary: Django management command to simplify building extjs and sencha touch apps with Sencha tools.
Home-page: https://github.com/espenak/djangosenchatools
Author: Espen Angell Kristiansen
Author-email: UNKNOWN
License: BSD
Platform: UNKNOWN
Classifier: Development Status :: 5 - Production/Stable
Classifier: Environment :: Web Environment
Classifier: Framework :: Django
Classifier: Intended Audience :: Developers
Classifier: License :: OSI Approved :: BSD License
Classifier: Operating System :: OS Independent
Classifier: Programming Language :: Python
